plottingtools_emilbowry/Plots.py
plottingtools_emilbowry/__init__.py
plottingtools_emilbowry/requirements.txt
plottingtools_emilbowry/plottingTools/_Plots.py
plottingtools_emilbowry/plottingTools/__init__.py
plottingtools_emilbowry/plottingTools/figure_methods.py
plottingtools_emilbowry/plottingTools/trace_methods.py
plottingtools_emilbowry/plottingTools/widget_container/__init__.py
plottingtools_emilbowry/plottingTools/widget_container/widget_container.py
plottingtools_emilbowry-0.2.0.dist-info/METADATA
plottingtools_emilbowry-0.2.0.dist-info/WHEEL
plottingtools_emilbowry-0.2.0.dist-info/licenses/LICENSE
plottingtools_emilbowry-0.2.0.dist-info/RECORD
