Metadata-Version: 2.4
Name: plottingtools_emilbowry
Version: 0.2.0
Author-email: Emil Bowry <emil.bowry@icloud.com>
License-Expression: MIT
License-File: LICENSE
Classifier: Operating System :: OS Independent
Classifier: Programming Language :: Python :: 3
Requires-Python: >=3.9
Requires-Dist: anywidget
Requires-Dist: jupyter
Requires-Dist: numpy
Requires-Dist: plotly
